LICENSE
MANIFEST.in
README.rst
pyproject.toml
setup.cfg
setup.py
versioneer.py
incense/__init__.py
incense/_version.py
incense/artifact.py
incense/experiment.py
incense/experiment_loader.py
incense/query_set.py
incense/utils.py
incense.egg-info/PKG-INFO
incense.egg-info/SOURCES.txt
incense.egg-info/dependency_links.txt
incense.egg-info/requires.txt
incense.egg-info/top_level.txt