Metadata-Version: 2.1
Name: incense
Version: 0.0.14
Summary: Interactively retrieve data from sacred experiments.
Home-page: https://github.com/JarnoRFB/incense
Author: Rüdiger Busche
Author-email: rbusche@uos.de
License: MIT
Classifier: Development Status :: 3 - Alpha
Classifier: Intended Audience :: Science/Research
Classifier: Programming Language :: Python :: 3.7
Classifier: Programming Language :: Python :: 3.8
Requires-Python: >=3.5
License-File: LICENSE
